mechy/FEM.py
mechy/__init__.py
mechy/fem.py
mechy/fem3d.py
mechy/untitled1.py
mechy-0.0.11.dist-info/METADATA
mechy-0.0.11.dist-info/WHEEL
mechy-0.0.11.dist-info/top_level.txt
mechy-0.0.11.dist-info/RECORD
