Metadata-Version: 2.1
Name: mechy
Version: 0.0.11
Summary: Core Engineering Analysis Functionalities
Home-page: UNKNOWN
Author: Sayan Biswas
Author-email: <biswas0235sayan@proton.me>
License: UNKNOWN
Keywords: python,engineering,finite element analysis,mechanics,stress,strain
Platform: UNKNOWN
Classifier: Development Status :: 1 - Planning
Classifier: Intended Audience :: Education
Classifier: Programming Language :: Python :: 3
Classifier: Operating System :: Unix
Classifier: Operating System :: MacOS :: MacOS X
Classifier: Operating System :: Microsoft :: Windows
Requires-Dist: numpy
Requires-Dist: matplotlib
